{"coupon_id":16743,"new_offer_status":"trash","new_offer_created_at":"2016-12-16 14:33:19","new_offer_published_at":"2016-12-16 14:33:19","new_offer_created_by":"mkoic@erstebank.com","new_offer_updated_at":"2017-02-28 02:00:02","new_offer_updated_by":"mkoic@erstebank.com","coupon_title":"Iglu \u0160port","coupon_slug":"iglu-sport","post_modified":"2017-02-28 02:00:02","offer_settings":{"offer_highlight":"A mountable discount","coupon_offer":"Mount that 10% discount every Tuesday","company_name":"Iglu \u0160port","dates":{"date_options":"List End Date","valid_start":"","valid_end":"20170228"},"company_logo":"http:\/\/most.dev\/wp-content\/uploads\/2016\/12\/iglusport_logo.jpg","featured_image":"","coupon_images":["http:\/\/most.dev\/wp-content\/uploads\/2016\/12\/iglusport_360x185.jpg"],"marks":[{"terms":"Unless otherwise stated above, for this offer to be valid, the cardmember shall:\r\n(1) pay with a Diners Club or any card within the partner network which is mutually agreed upon, in writing by the parties;\r\n(2) show the offer in print or mobile phone; and\r\n(3) if explicitly required by the merchant, enter the promotional code if purchasing online.\r\nOnly one offer per cardmember can be used and cannot be combined with any other offer, unless otherwise stated. This offer is non-refundable, transferable and carries no monetary alternative.","acceptance_mark_image":"http:\/\/most.dev\/wp-content\/uploads\/2014\/11\/diners_acceptance.png","id":6134,"name":"Diners Club Acceptance Mark"}],"terms":"","locations":"","company_email":"iglusport@iglusport.hr","company_phone_number":"385 13700434","company_website":"http:\/\/www.iglusport.hr","merchant_phone_prefix":"+385","merchant_phone_number":"13700434"},"offer_destination":[{"name":"Croatia","slug":"croatia","term_id":374,"term_taxonomy_id":375}],"offer_tags":[{"name":"Shopping","slug":"shop","term_id":5,"term_taxonomy_id":5}],"slider_coupons":[],"remote_sites":[{"name":"Diners Club Privileges","slug":"dinersclubprivileges","term_id":240,"term_taxonomy_id":240}],"featured":[],"offer_sticky_option":false,"geo_location":{"address":"Ul. Velimira \u0160korpika 11, 10000, Zagreb, Hrvatska","lat":45.8108024,"lng":15.859924},"geolocation_v2":[{"address":"Ul. Velimira \u0160korpika 11, 10000, Zagreb, Hrvatska","body":"10000, Zagreb, Hrvatska","correctedAddress":"Ul. Velimira \u0160korpika 11, 10000, Zagreb, Hrvatska","iconid":null,"point":{"lat":45.8108024,"lng":15.859924},"poly":null,"kml":null,"title":"Ul. Velimira \u0160korpika 11","type":null,"viewport":{"sw":{"lat":45.809454619708,"lng":15.858565769709},"ne":{"lat":45.812152580292,"lng":15.861263730292}},"postid":null,"url":null}],"price_range":"","small_business":0,"cuisine_type":""}